[
  { "date": "2026-01-01", "name": "Año Nuevo", "isBridge": false },
  { "date": "2026-02-16", "name": "Carnaval", "isBridge": false },
  { "date": "2026-02-17", "name": "Carnaval", "isBridge": false },
  { "date": "2026-03-24", "name": "Día Nacional de la Memoria", "isBridge": false },
  { "date": "2026-04-02", "name": "Día del Veterano y de los Caídos", "isBridge": false },
  { "date": "2026-04-03", "name": "Viernes Santo", "isBridge": false },
  { "date": "2026-05-01", "name": "Día del Trabajador", "isBridge": false },
  { "date": "2026-05-25", "name": "Día de la Revolución de Mayo", "isBridge": false },
  { "date": "2026-06-17", "name": "Paso a la Inmortalidad del Gral. Güemes", "isBridge": false },
  { "date": "2026-06-20", "name": "Paso a la Inmortalidad del Gral. Belgrano", "isBridge": false },
  { "date": "2026-07-09", "name": "Día de la Independencia", "isBridge": false },
  { "date": "2026-08-17", "name": "Paso a la Inmortalidad del Gral. San Martín", "isBridge": false },
  { "date": "2026-10-12", "name": "Día del Respeto a la Diversidad Cultural", "isBridge": false },
  { "date": "2026-11-23", "name": "Día de la Soberanía Nacional", "isBridge": false },
  { "date": "2026-12-08", "name": "Inmaculada Concepción de María", "isBridge": false },
  { "date": "2026-12-25", "name": "Navidad", "isBridge": false },
  { "date": "2027-01-01", "name": "Año Nuevo", "isBridge": false },
  { "date": "2027-02-08", "name": "Carnaval", "isBridge": false },
  { "date": "2027-02-09", "name": "Carnaval", "isBridge": false },
  { "date": "2027-03-24", "name": "Día Nacional de la Memoria", "isBridge": false },
  { "date": "2027-03-26", "name": "Viernes Santo", "isBridge": false },
  { "date": "2027-04-02", "name": "Día del Veterano y de los Caídos", "isBridge": true },
  { "date": "2027-05-01", "name": "Día del Trabajador", "isBridge": false },
  { "date": "2027-05-25", "name": "Día de la Revolución de Mayo", "isBridge": false },
  { "date": "2027-06-17", "name": "Paso a la Inmortalidad del Gral. Güemes", "isBridge": true },
  { "date": "2027-06-20", "name": "Paso a la Inmortalidad del Gral. Belgrano", "isBridge": false },
  { "date": "2027-07-09", "name": "Día de la Independencia", "isBridge": false },
  { "date": "2027-08-16", "name": "Paso a la Inmortalidad del Gral. San Martín", "isBridge": true },
  { "date": "2027-10-11", "name": "Día del Respeto a la Diversidad Cultural", "isBridge": true },
  { "date": "2027-11-22", "name": "Día de la Soberanía Nacional", "isBridge": true },
  { "date": "2027-12-08", "name": "Inmaculada Concepción de María", "isBridge": false },
  { "date": "2027-12-25", "name": "Navidad", "isBridge": false },
  { "date": "2028-01-01", "name": "Año Nuevo", "isBridge": false },
  { "date": "2028-02-28", "name": "Carnaval", "isBridge": false },
  { "date": "2028-02-29", "name": "Carnaval", "isBridge": false },
  { "date": "2028-03-24", "name": "Día Nacional de la Memoria", "isBridge": false },
  { "date": "2028-04-14", "name": "Viernes Santo", "isBridge": false },
  { "date": "2028-04-02", "name": "Día del Veterano y de los Caídos", "isBridge": false },
  { "date": "2028-05-01", "name": "Día del Trabajador", "isBridge": false },
  { "date": "2028-05-25", "name": "Día de la Revolución de Mayo", "isBridge": false },
  { "date": "2028-06-17", "name": "Paso a la Inmortalidad del Gral. Güemes", "isBridge": false },
  { "date": "2028-06-20", "name": "Paso a la Inmortalidad del Gral. Belgrano", "isBridge": false },
  { "date": "2028-07-09", "name": "Día de la Independencia", "isBridge": false },
  { "date": "2028-08-21", "name": "Paso a la Inmortalidad del Gral. San Martín", "isBridge": true },
  { "date": "2028-10-16", "name": "Día del Respeto a la Diversidad Cultural", "isBridge": true },
  { "date": "2028-11-20", "name": "Día de la Soberanía Nacional", "isBridge": true },
  { "date": "2028-12-08", "name": "Inmaculada Concepción de María", "isBridge": false },
  { "date": "2028-12-25", "name": "Navidad", "isBridge": false }
]
